CHANGES.txt
LICENSE.txt
MANIFEST.in
README.md
setup.py
bankdownloads/__init__.py
bankdownloads/admin.py
bankdownloads/management/__init__.py
bankdownloads/management/commands/__init__.py
bankdownloads/management/commands/bankdownloads_notifier.py
bankdownloads/management/commands/bankdownloads_processor.py
bankdownloads/models/__init__.py
bankdownloads/models/bankdownload.py
bankdownloads/utils/__init__.py
bankdownloads/utils/ofx.py
django_bankdownloads.egg-info/PKG-INFO
django_bankdownloads.egg-info/SOURCES.txt
django_bankdownloads.egg-info/dependency_links.txt
django_bankdownloads.egg-info/not-zip-safe
django_bankdownloads.egg-info/top_level.txt
docs/index.txt