Metadata-Version: 1.0
Name: django-bankdownloads
Version: 0.1.0
Summary: UNKNOWN
Home-page: http://celeryproject.org
Author: Evan Davey
Author-email: evan.davey@cochranedavey.com
License: CC-SA-NC
Platform: any
Classifier: Development Status :: 3 - Alpha
Classifier: Environment :: Web Environment
Classifier: Framework :: Django
Classifier: Intended Audience :: Developers
Classifier: License :: OSI Approved :: BSD License
Classifier: Operating System :: OS Independent
Classifier: Programming Language :: Python
Classifier: Topic :: Utilities
